flowml/__init__.py
flowml/models/__init__.py
flowml/models/base.py
flowml/models/pytorch/__init__.py
flowml/models/pytorch/architectures/lstm.py
flowml/models/pytorch/architectures/mlp.py
flowml/models/pytorch/architectures/transformer.py
flowml/models/pytorch/base.py
flowml/models/pytorch/drivers/lstm_autoregressive.py
flowml/models/pytorch/drivers/lstm_direct_regressor.py
flowml/models/pytorch/drivers/mlp_regressor.py
flowml/models/pytorch/drivers/transformer_regressor.py
flowml/models/pytorch/utils.py
flowml/models/xgboost/__init__.py
flowml/models/xgboost/regressor.py
flowml/pipefill.py
flowml/tensorboard.py
flowml/utils.py
flowml-0.1.1.dist-info/LICENSE
flowml-0.1.1.dist-info/METADATA
flowml-0.1.1.dist-info/WHEEL
flowml-0.1.1.dist-info/RECORD
