Metadata-Version: 2.3
Name: flowml
Version: 0.1.1
Summary: The machine learning components designed for use in Flowdapt.
License: Apache-2.0
Author: Emergent Methods
Author-email: contact@emergentmethods.ai
Requires-Python: >=3.11,<4.0
Classifier: Development Status :: 3 - Alpha
Classifier: Environment :: Web Environment
Classifier: Intended Audience :: Developers
Classifier: License :: OSI Approved :: Apache Software License
Classifier: License :: OSI Approved :: MIT License
Classifier: Operating System :: OS Independent
Classifier: Programming Language :: Python :: 3
Classifier: Programming Language :: Python :: 3.11
Classifier: Programming Language :: Python :: 3.12
Classifier: Programming Language :: Python :: 3.13
Classifier: Programming Language :: Python :: 3 :: Only
Classifier: Programming Language :: Python :: 3.10
Classifier: Topic :: Scientific/Engineering :: Artificial Intelligence
Classifier: Topic :: Software Development :: Libraries :: Application Frameworks
Classifier: Topic :: System :: Distributed Computing
Classifier: Topic :: Utilities
Requires-Dist: cloudpickle (==3.1.1)
Requires-Dist: datasieve (>=0.1.6,<0.2.0)
Requires-Dist: flowdapt (>=0.1.28,<0.2.0)
Requires-Dist: pandas (>=2.0.2,<3.0.0)
Requires-Dist: pynvml (>=12.0.0,<13.0.0)
Requires-Dist: scikit-learn (>=1.6.1,<2.0.0)
Requires-Dist: tensorboard (>=2.19.0,<3.0.0)
Requires-Dist: torch (>=2.7.0,<3.0.0)
Requires-Dist: xgboost (>=1.7.2,<2.0.0)
